epflldap/__init__.py
epflldap/_version.py
epflldap/db/__init__.py
epflldap/db/ldapdb.py
epflldap/users/__init__.py
epflldap/users/address.py
epflldap/users/user.py
epflldap/users/users.py
epflldap-0.4.1.dist-info/LICENSE
epflldap-0.4.1.dist-info/METADATA
epflldap-0.4.1.dist-info/WHEEL
epflldap-0.4.1.dist-info/top_level.txt
epflldap-0.4.1.dist-info/RECORD
