Metadata-Version: 2.1
Name: epflldap
Version: 0.4.1
Summary: Ce module permet de d'analyser les données d'LDAP à l'EPFL
Home-page: UNKNOWN
Author: Raphaël Rey
Author-email: raphael.rey@epfl.ch
License: MIT
Platform: UNKNOWN
Classifier: Programming Language :: Python :: 3
Requires-Dist: pandas
Requires-Dist: ldap3
